[{"timestamp": "2025-11-23T20:50:10.542134", "download": 10.74, "upload": 12.56, "ping": 74.6, "server": "Darnytsia.Net"}, {"timestamp": "2025-11-23T21:09:20.098465", "download": 8.38, "upload": 14.42, "ping": 42.4, "server": "UTELS LLC"}, {"timestamp": "2025-11-23T21:21:42.747662", "download": 5.48, "upload": 10.38, "ping": 102.3, "server": "Domonet"}, {"timestamp": "2025-11-23T21:22:28.331178", "download": 5.65, "upload": 8.54, "ping": 84.7, "server": "Darnytsia.Net"}, {"timestamp": "2025-11-23T21:40:41.567401", "download": 6.08, "upload": 1.94, "ping": 78.1, "server": "Domonet"}, {"timestamp": "2025-11-23T21:41:40.884563", "download": 11.32, "upload": 2.64, "ping": 102.9, "server": "Volia"}, {"timestamp": "2025-11-23T21:42:36.307960", "download": 10.57, "upload": 3.09, "ping": 37.5, "server": "OmegaTV"}, {"timestamp": "2025-11-23T21:43:39.237724", "download": 10.13, "upload": 4.33, "ping": 79.7, "server": "UTELS LLC"}, {"timestamp": "2025-11-23T21:44:42.957218", "download": 8.06, "upload": 1.78, "ping": 59.4, "server": "OmegaTV"}, {"timestamp": "2025-11-23T21:45:39.874247", "download": 11.28, "upload": 3.93, "ping": 34.2, "server": "UTELS LLC"}, {"timestamp": "2025-11-23T21:46:40.823528", "download": 8.94, "upload": 2.01, "ping": 134.7, "server": "Domonet"}, {"timestamp": "2025-11-23T21:47:39.629882", "download": 9.54, "upload": 3.17, "ping": 101.1, "server": "Volia"}, {"timestamp": "2025-11-23T21:48:39.344901", "download": 16.83, "upload": 9.11, "ping": 102.4, "server": "OmegaTV"}, {"timestamp": "2025-11-23T21:49:40.019017", "download": 10.92, "upload": 1.81, "ping": 102.3, "server": "OmegaTV"}, {"timestamp": "2025-11-23T21:50:39.489410", "download": 9.45, "upload": 4.69, "ping": 77.3, "server": "Volia"}, {"timestamp": "2025-11-23T21:51:39.444473", "download": 10.15, "upload": 4.91, "ping": 101.6, "server": "UTELS LLC"}, {"timestamp": "2025-11-23T21:52:42.616958", "download": 12.22, "upload": 6.46, "ping": 42.4, "server": "Domonet"}, {"timestamp": "2025-11-23T21:53:42.209112", "download": 13.79, "upload": 2.08, "ping": 67.8, "server": "Domonet"}, {"timestamp": "2025-11-23T21:54:42.191511", "download": 6.05, "upload": 2.22, "ping": 56.1, "server": "OmegaTV"}, {"timestamp": "2025-11-23T21:55:41.595367", "download": 6.54, "upload": 2.0, "ping": 100.7, "server": "Volia"}, {"timestamp": "2025-11-23T21:56:43.323147", "download": 14.17, "upload": 1.47, "ping": 77.9, "server": "OmegaTV"}, {"timestamp": "2025-11-23T21:57:39.223903", "download": 11.4, "upload": 3.82, "ping": 102.1, "server": "Volia"}, {"timestamp": "2025-11-23T21:58:41.947893", "download": 8.82, "upload": 2.17, "ping": 102.1, "server": "Volia"}, {"timestamp": "2025-11-23T21:59:41.950115", "download": 3.83, "upload": 1.61, "ping": 74.7, "server": "UTELS LLC"}, {"timestamp": "2025-11-23T22:05:39.744288", "download": 4.24, "upload": 2.19, "ping": 42.9, "server": "Volia"}, {"timestamp": "2025-11-23T22:06:36.882881", "download": 5.43, "upload": 2.41, "ping": 32.9, "server": "Volia"}, {"timestamp": "2025-11-23T22:07:36.229663", "download": 5.36, "upload": 7.48, "ping": 35.4, "server": "Domonet"}, {"timestamp": "2025-11-23T22:08:37.944118", "download": 6.14, "upload": 5.38, "ping": 36.7, "server": "Volia"}, {"timestamp": "2025-11-23T22:09:37.772760", "download": 6.95, "upload": 5.99, "ping": 31.0, "server": "Domonet"}, {"timestamp": "2025-11-23T22:10:46.763960", "download": 5.93, "upload": 2.88, "ping": 39.5, "server": "UTELS LLC"}, {"timestamp": "2025-11-23T22:12:34.984150", "download": 90.13, "upload": 94.2, "ping": 3.4, "server": "KPI-Telecom"}, {"timestamp": "2025-11-23T22:13:34.847548", "download": 83.67, "upload": 94.03, "ping": 3.0, "server": "Gigabit-Net LLC"}, {"timestamp": "2025-11-23T22:14:34.703500", "download": 91.32, "upload": 94.03, "ping": 2.4, "server": "Gigabit-Net LLC"}, {"timestamp": "2025-11-23T22:15:34.695276", "download": 91.02, "upload": 94.22, "ping": 2.6, "server": "Gigabit-Net LLC"}, {"timestamp": "2025-11-23T22:16:34.905219", "download": 94.26, "upload": 93.02, "ping": 2.8, "server": "KPI-Telecom"}, {"timestamp": "2025-11-23T22:17:35.131124", "download": 94.09, "upload": 94.07, "ping": 3.1, "server": "Volia"}, {"timestamp": "2025-11-23T22:18:34.863258", "download": 94.55, "upload": 94.25, "ping": 5.9, "server": "Volia"}, {"timestamp": "2025-11-23T23:18:59.761374", "download": 10.02, "upload": 39.24, "ping": 24.4, "server": "KPI-Telecom"}, {"timestamp": "2025-11-24T11:55:30.635354", "download": 827.9, "upload": 896.28, "ping": 2.2, "server": "Domonet"}, {"timestamp": "2025-11-24T12:25:27.361759", "download": 912.98, "upload": 865.24, "ping": 2.3, "server": "NashNet LLC"}, {"timestamp": "2025-11-24T13:11:02.138969", "download": 891.11, "upload": 899.6, "ping": 2.5, "server": "OmegaTV"}, {"timestamp": "2025-11-24T13:25:27.483987", "download": 908.71, "upload": 885.99, "ping": 2.1, "server": "OmegaTV"}, {"timestamp": "2025-11-24T14:25:27.695253", "download": 820.12, "upload": 894.0, "ping": 2.4, "server": "Domonet"}, {"timestamp": "2025-11-24T15:25:38.282935", "download": 176.26, "upload": 215.54, "ping": 5.2, "server": "Domonet"}, {"timestamp": "2025-11-24T16:09:56.729629", "download": 632.22, "upload": 332.87, "ping": 2.0, "server": "UACITY LLC"}, {"timestamp": "2025-11-24T16:25:27.406363", "download": 917.09, "upload": 846.21, "ping": 1.6, "server": "Domonet"}, {"timestamp": "2025-11-24T17:25:27.534440", "download": 913.22, "upload": 873.05, "ping": 2.2, "server": "KyivLink"}, {"timestamp": "2025-11-24T18:25:27.446546", "download": 896.88, "upload": 871.97, "ping": 2.3, "server": "Domonet"}, {"timestamp": "2025-11-24T19:10:30.579488", "download": 919.49, "upload": 870.15, "ping": 2.4, "server": "Domonet"}, {"timestamp": "2025-11-24T21:41:24.009897", "download": 91.77, "upload": 91.37, "ping": 2.6, "server": "IPnet"}, {"timestamp": "2025-11-25T21:42:05.914066", "download": 94.61, "upload": 94.78, "ping": 2.8, "server": "Lanet Network Ltd"}, {"timestamp": "2025-11-25T22:41:07.978781", "download": 90.58, "upload": 94.69, "ping": 4.1, "server": "ISP OmegaTelecom"}, {"timestamp": "2025-11-26T12:39:37.948727", "download": 918.14, "upload": 876.79, "ping": 2.2, "server": "OmegaTV"}, {"timestamp": "2025-11-26T13:39:38.397421", "download": 782.99, "upload": 909.18, "ping": 2.3, "server": "Gigabit-Net LLC"}, {"timestamp": "2025-11-26T14:25:10.789950", "download": 394.25, "upload": 236.68, "ping": 5.4, "server": "Gigatrans UA"}, {"timestamp": "2025-11-26T14:39:38.335850", "download": 803.13, "upload": 869.56, "ping": 2.2, "server": "Gigatrans UA"}, {"timestamp": "2025-11-26T14:54:34.100442", "download": 190.78, "upload": 212.88, "ping": 1.6, "server": "RETN"}, {"timestamp": "2025-11-26T15:39:46.383033", "download": 354.75, "upload": 291.48, "ping": 6.0, "server": "Gigabit-Net LLC"}, {"timestamp": "2025-11-26T16:39:46.912799", "download": 351.44, "upload": 278.11, "ping": 5.4, "server": "Gigatrans UA"}, {"timestamp": "2025-11-26T17:39:47.940788", "download": 323.04, "upload": 246.52, "ping": 5.2, "server": "IPnet"}, {"timestamp": "2025-11-26T18:39:46.887995", "download": 353.14, "upload": 274.54, "ping": 3.9, "server": "IPnet"}, {"timestamp": "2025-11-26T19:39:45.945487", "download": 380.41, "upload": 276.65, "ping": 3.7, "server": "IPnet"}, {"timestamp": "2025-11-27T12:45:40.151323", "download": 893.05, "upload": 895.53, "ping": 2.4, "server": "OmegaTV"}, {"timestamp": "2025-11-27T13:45:40.136450", "download": 895.5, "upload": 887.57, "ping": 2.2, "server": "Domonet"}, {"timestamp": "2025-11-27T14:45:40.322948", "download": 856.25, "upload": 888.03, "ping": 2.7, "server": "Campus-City"}, {"timestamp": "2025-11-27T15:45:40.110929", "download": 915.63, "upload": 841.48, "ping": 2.2, "server": "Domonet"}, {"timestamp": "2025-11-27T16:45:40.300706", "download": 898.65, "upload": 897.2, "ping": 2.3, "server": "UTELS LLC"}, {"timestamp": "2025-11-27T17:16:45.750162", "download": 915.54, "upload": 892.47, "ping": 2.4, "server": "PrJSC VF Ukraine"}, {"timestamp": "2025-11-27T17:17:07.412898", "download": 911.49, "upload": 894.86, "ping": 2.1, "server": "PrJSC VF Ukraine"}, {"timestamp": "2025-11-27T17:18:16.411727", "download": 886.7, "upload": 889.12, "ping": 2.4, "server": "PrJSC VF Ukraine"}, {"timestamp": "2025-11-27T17:18:24.267726", "download": 903.0, "upload": 869.8, "ping": 1.8, "server": "PrJSC VF Ukraine"}, {"timestamp": "2025-11-28T11:39:38.278108", "download": 100.78, "upload": 251.21, "ping": 5.8, "server": "IPnet"}, {"timestamp": "2025-11-28T12:33:26.278363", "download": 290.81, "upload": 299.32, "ping": 5.3, "server": "IPnet"}, {"timestamp": "2025-11-28T12:33:41.189782", "download": 378.73, "upload": 313.83, "ping": 4.3, "server": "IPnet"}, {"timestamp": "2025-11-28T13:33:17.238796", "download": 876.07, "upload": 881.47, "ping": 2.0, "server": "IPnet"}, {"timestamp": "2025-11-28T14:33:17.120683", "download": 912.06, "upload": 846.81, "ping": 2.1, "server": "NashNet LLC"}, {"timestamp": "2025-11-28T15:33:17.155835", "download": 914.65, "upload": 876.91, "ping": 2.1, "server": "NashNet LLC"}, {"timestamp": "2025-11-28T16:33:17.725217", "download": 764.65, "upload": 887.2, "ping": 2.5, "server": "NashNet LLC"}, {"timestamp": "2025-11-28T17:33:17.443604", "download": 845.66, "upload": 860.88, "ping": 2.0, "server": "Domonet"}, {"timestamp": "2025-11-28T18:33:17.158976", "download": 883.66, "upload": 878.97, "ping": 2.5, "server": "KPI-Telecom"}, {"timestamp": "2025-12-03T14:37:17.311161", "download": 855.02, "upload": 875.51, "ping": 2.5, "server": "IPnet"}, {"timestamp": "2025-12-03T14:52:48.543047", "download": 31.4, "upload": 32.77, "ping": 20.0, "server": "VSELINK LLC"}, {"timestamp": "2025-12-08T18:27:34.137507", "download": 5.76, "upload": 9.01, "ping": 17.4, "server": "IPnet"}, {"timestamp": "2025-12-08T18:27:55.151854", "download": 8.96, "upload": 3.68, "ping": 43.2, "server": "Volia"}, {"timestamp": "2025-12-08T18:31:13.588896", "download": 716.3, "upload": 880.2, "ping": 1.5, "server": "IPnet"}, {"timestamp": "2025-12-08T18:32:29.743639", "download": 881.74, "upload": 821.37, "ping": 1.7, "server": "IPnet"}, {"timestamp": "2025-12-08T18:35:12.331318", "download": 915.22, "upload": 871.49, "ping": 1.8, "server": "IPnet"}, {"timestamp": "2025-12-08T18:36:02.750541", "download": 848.51, "upload": 903.2, "ping": 1.4, "server": "IPnet"}, {"timestamp": "2025-12-09T15:21:37.556393", "download": 849.33, "upload": 905.2, "ping": 2.2, "server": "Domonet"}, {"timestamp": "2025-12-10T11:00:47.584567", "download": 608.45, "upload": 277.55, "ping": 2.0, "server": "UACITY LLC"}, {"timestamp": "2025-12-10T13:36:39.778032", "download": 749.16, "upload": 777.36, "ping": 2.1, "server": "NLine LLC"}, {"timestamp": "2025-12-11T14:09:23.605306", "download": 909.62, "upload": 829.0, "ping": 2.3, "server": "ISP OmegaTelecom"}, {"timestamp": "2025-12-11T14:10:06.825176", "download": 929.06, "upload": 893.17, "ping": 2.2, "server": "Gigabit-Net LLC"}, {"timestamp": "2025-12-11T14:22:47.428757", "download": 919.28, "upload": 899.99, "ping": 1.6, "server": "Gigabit-Net LLC"}, {"timestamp": "2025-12-11T22:49:37.264683", "download": 93.0, "upload": 94.68, "ping": 3.1, "server": "Gigabit-Net LLC"}]